fallexplorer/__init__.py
fallexplorer/main.py
fallexplorer-1.0.0.dist-info/LICENSE
fallexplorer-1.0.0.dist-info/METADATA
fallexplorer-1.0.0.dist-info/WHEEL
fallexplorer-1.0.0.dist-info/top_level.txt
fallexplorer-1.0.0.dist-info/RECORD
