Metadata-Version: 2.2
Name: fallexplorer
Version: 1.0.0
Summary: Outil de pentesting avec reconnaissance passive et tests actifs
Author: Ton Nom
Author-email: contact@openstudy.me
Classifier: Programming Language :: Python :: 3
Classifier: License :: OSI Approved :: MIT License
Classifier: Operating System :: OS Independent
License-File: LICENSE
Requires-Dist: requests
Requires-Dist: python-whois
Requires-Dist: dnspython
Requires-Dist: builtwith
Requires-Dist: tabulate
Requires-Dist: rich
Dynamic: author
Dynamic: author-email
Dynamic: classifier
Dynamic: description
Dynamic: description-content-type
Dynamic: requires-dist
Dynamic: summary
